zoteroapi/__init__.py
zoteroapi/client.py
zoteroapi/exceptions.py
zoteroapi-0.1.1.dist-info/METADATA
zoteroapi-0.1.1.dist-info/WHEEL
zoteroapi-0.1.1.dist-info/licenses/LICENSE
zoteroapi-0.1.1.dist-info/RECORD
