Metadata-Version: 2.3
Name: zoteroapi
Version: 0.1.1
Summary: This is a Python client library for accessing the local Zotero server API.
Project-URL: Homepage, https://github.com/yourusername/zotero-local-api
Author: Tao Zhang
License: MIT License
Classifier: License :: OSI Approved :: MIT License
Classifier: Operating System :: OS Independent
Classifier: Programming Language :: Python :: 3
Requires-Python: >=3.7
Requires-Dist: requests>=2.25.0
